.coveragerc
.gitignore
.landscape.yml
CONTRIBUTING.rst
DESIGN.rst
LICENSE.txt
MANIFEST.in
Makefile
README.rst
requirements-analysis.txt
requirements-docs.txt
requirements-tests.txt
setup.py
tox.ini
asynctelnet/.gitignore
asynctelnet/__init__.py
asynctelnet/accessories.py
asynctelnet/client.py
asynctelnet/client_base.py
asynctelnet/client_shell.py
asynctelnet/relay_server.py
asynctelnet/server.py
asynctelnet/server_base.py
asynctelnet/server_shell.py
asynctelnet/slc.py
asynctelnet/stream.py
asynctelnet/telopt.py
asynctelnet.egg-info/PKG-INFO
asynctelnet.egg-info/SOURCES.txt
asynctelnet.egg-info/dependency_links.txt
asynctelnet.egg-info/entry_points.txt
asynctelnet.egg-info/requires.txt
asynctelnet.egg-info/top_level.txt
asynctelnet.egg-info/zip-safe
asynctelnet/example/__init__.py
docs/Makefile
docs/api.rst
docs/conf.py
docs/contributing.rst
docs/example_linemode.py
docs/example_readline.py
docs/history.rst
docs/index.rst
docs/intro.rst
docs/make.bat
docs/rfcs.rst
docs/api/accessories.rst
docs/api/client.rst
docs/api/client_base.rst
docs/api/client_shell.rst
docs/api/server.rst
docs/api/server_base.rst
docs/api/server_shell.rst
docs/api/slc.rst
docs/api/stream.rst
docs/api/telopt.rst
docs/sphinxext/github.py
examples/__init__.py
examples/client
examples/serve.py
examples/server
examples/wargame_client.py
examples/wargame_server.py
tests/accessories.py
tests/test_accessories.py
tests/test_charset.py
tests/test_core.py
tests/test_encoding.py
tests/test_environ.py
tests/test_linemode.py
tests/test_naws.py
tests/test_reader.py
tests/test_shell.py
tests/test_timeout.py
tests/test_tspeed.py
tests/test_ttype.py
tests/test_writer.py
tests/test_xdisploc.py