Metadata-Version: 1.1
Name: asynctelnet
Version: 0.2.5
Summary: Python 3 anyio Telnet server and client Protocol library
Home-page: http://asynctelnet.readthedocs.io/
Author: Matthias Urlichs
Author-email: matthias@urlichs.de
License: ISC
Keywords: telnet,server,client,bbs,mud,utf8,cp437,api,library,anyio,trio,asyncio,talker
Platform: any
Classifier: License :: OSI Approved :: ISC License (ISCL)
Classifier: Programming Language :: Python :: 3.8
Classifier: Programming Language :: Python :: 3.9
Classifier: Intended Audience :: Developers
Classifier: Development Status :: 3 - Alpha
Classifier: Topic :: System :: Networking
Classifier: Topic :: Terminals :: Telnet
Classifier: Topic :: System :: Shells
Classifier: Topic :: Internet
